[
  {
    "loc": [0, 1],
    "title": "Pure or impure ?"
  },
  {
    "loc": [0, 1],
    "title": "Pure or impure ?",
    "note": "Pure"
  },
  {
    "loc": [2, 6],
    "title": "Pure or impure ?"
  },
  {
    "loc": [2, 6],
    "title": "Pure or impure ?",
    "note": "Impure"
  },
  {
    "loc": [7, 9],
    "title": "Pure or impure ?"
  },
  {
    "loc": [7, 9],
    "title": "Pure or impure ?",
    "note": "Impure"
  },
  {
    "loc": [9, 10],
    "title": "Result ?",
    "note": "15 ?"
  },
  {
    "loc": [10, 12],
    "title": "Result ?",
    "note": "8AXAEngineeringSummit"
  },
  {
    "loc": [13, 14],
    "title": "Pure"
  },
  {
    "loc": [15, 17],
    "title": "Pure or impure ?"
  },
  {
    "loc": [15, 17],
    "title": "Pure or impure ?",
    "note": "Impure"
  },
  {
    "loc": [18, 20],
    "title": "Pure"
  }
]
